{
    "name": "root0",
    "inputs": [],
    "outputs": [
        "root0_0",
        "root0_1"
    ],
    "kids": [
        {
            "name": "root0_0",
            "inputs": [
                "root0"
            ],
            "outputs": [
                "root0_0_0"
            ],
            "kids": [
                {
                    "name": "root0_0_0",
                    "inputs": [
                        "root0_0"
                    ],
                    "outputs": [],
                    "kids": []
                }
            ]
        },
        {
            "name": "root0_1",
            "inputs": [
                "root0"
            ],
            "outputs": [
                "root0_1_0",
                "root0_1_1"
            ],
            "kids": [
                {
                    "name": "root0_1_0",
                    "inputs": [
                        "root0_1"
                    ],
                    "outputs": [
                        "root0_1_0_0"
                    ],
                    "kids": [
                        {
                            "name": "root0_1_0_0",
                            "inputs": [
                                "root0_1_0"
                            ],
                            "outputs": [],
                            "kids": []
                        }
                    ]
                },
                {
                    "name": "root0_1_1",
                    "inputs": [
                        "root0_1"
                    ],
                    "outputs": [],
                    "kids": []
                }
            ]
        }
    ]
}